reahl/workstation/__init__.py
reahl/workstation/dockersupport.py
reahl/workstation/ngroksupport.py
reahl/workstation/xprasupport.py
reahl/workstation_dev/__init__.py
reahl/workstation_dev/test_ngrok.py
reahl/workstation_dev/test_xpra.py
reahl_workstation-7.0.3.dist-info/LICENSE
reahl_workstation-7.0.3.dist-info/METADATA
reahl_workstation-7.0.3.dist-info/WHEEL
reahl_workstation-7.0.3.dist-info/entry_points.txt
reahl_workstation-7.0.3.dist-info/reahl-component.toml
reahl_workstation-7.0.3.dist-info/top_level.txt
reahl_workstation-7.0.3.dist-info/RECORD
